python_with_braces/__init__.py
python_with_braces/__main__.py
python_with_braces/core.py
python_with_braces/snake_game.py
python_with_braces-0.1.2.data/data/LICENSE
python_with_braces-0.1.2.data/data/README.md
python_with_braces-0.1.2.data/data/requirements.txt
python_with_braces-0.1.2.dist-info/licenses/LICENSE
python_with_braces-0.1.2.dist-info/METADATA
python_with_braces-0.1.2.dist-info/WHEEL
python_with_braces-0.1.2.dist-info/entry_points.txt
python_with_braces-0.1.2.dist-info/top_level.txt
python_with_braces-0.1.2.dist-info/RECORD
