Metadata-Version: 2.4
Name: python_with_braces
Version: 0.1.2
Summary: 让Python支持大括号语法的预处理器 (PWB)
Home-page: https://github.com/pythonwithbraces/python_with_braces
Author: Python With Braces Team
Author-email: Python With Braces Team <contact@pythonwithbraces.com>
License: MIT License
Project-URL: Homepage, https://github.com/pythonwithbraces/python_with_braces
Project-URL: Source, https://github.com/pythonwithbraces/python_with_braces
Keywords: python,braces,syntax,preprocessor,PWB
Classifier: Development Status :: 3 - Alpha
Classifier: Intended Audience :: Developers
Classifier: License :: OSI Approved :: MIT License
Classifier: Programming Language :: Python :: 3
Classifier: Programming Language :: Python :: 3.6
Classifier: Programming Language :: Python :: 3.7
Classifier: Programming Language :: Python :: 3.8
Classifier: Programming Language :: Python :: 3.9
Classifier: Programming Language :: Python :: 3.10
Classifier: Programming Language :: Python :: 3.11
Classifier: Programming Language :: Python :: 3.12
Classifier: Programming Language :: Python :: 3.13
Classifier: Topic :: Software Development :: Libraries :: Python Modules
Classifier: Topic :: Utilities
Requires-Python: >=3.6
License-File: LICENSE
Dynamic: author
Dynamic: home-page
Dynamic: license-file
Dynamic: requires-python
